BasicLibrary/__init__.py
BasicLibrary/config_utils.py
BasicLibrary/deal_float.py
BasicLibrary/logger_utils.py
BasicLibrary/mysql_utils.py
BasicLibrary/random_credit_card.py
BasicLibrary/request_utils.py
BasicLibrary/stageplan_utils.py
BasicLibrary/identity_random/__init__.py
BasicLibrary/identity_random/constant.py
BasicLibrary/identity_random/identity.py
samples/__init__.py
samples/demo_01.py
samples/demo_02.py
samples/demo_03.py
samples/demo_04.py
samples/demo_05.py
samples/demo_06.py
samples/demo_07.py
samples/demo_08.py
BasicLibrary-1.2.6.dist-info/LICENSE
BasicLibrary-1.2.6.dist-info/METADATA
BasicLibrary-1.2.6.dist-info/WHEEL
BasicLibrary-1.2.6.dist-info/top_level.txt
BasicLibrary-1.2.6.dist-info/RECORD
