Metadata-Version: 2.1
Name: BasicLibrary
Version: 1.2.6
Summary: python接口自动化框架基础模块
Home-page: UNKNOWN
Author: chenjuan
Author-email: 15073140749@163.com
License: UNKNOWN
Platform: UNKNOWN
Classifier: Programming Language :: Python :: 3
Classifier: License :: OSI Approved :: MIT License
Classifier: Operating System :: OS Independent
Requires-Python: >=3.6
Requires-Dist: nb-log
Requires-Dist: pymysql
Requires-Dist: configparser
Requires-Dist: pytest
Requires-Dist: pytest-ordering
Requires-Dist: allure-pytest
